[
    {
        "label": "RIGHT LEG",
        "x": 59.19999999999999,
        "y": 89.8
    },
    {
        "label": "RIGHT KNEE",
        "x": 58.1,
        "y": 86.0
    },
    {
        "label": "RIGHT HIP",
        "x": 58.800000000000004,
        "y": 81.5
    },
    {
        "label": "RIGHT SHOULDER",
        "x": 57.49999999999999,
        "y": 70.2
    },
    {
        "label": "RIGHT ELBOW",
        "x": 54.800000000000004,
        "y": 75.1
    },
    {
        "label": "RIGHT ARM",
        "x": 54.4,
        "y": 79.3
    },
    {
        "label": "RIGHT EYE",
        "x": 59.800000000000004,
        "y": 65.6
    },
    {
        "label": "RIGHT EAR",
        "x": 55.9,
        "y": 62.2
    },
    {
        "label": "LEFT LEG",
        "x": 68.80000000000001,
        "y": 89.8
    },
    {
        "label": "LEFT KNEE",
        "x": 69.9,
        "y": 86.0
    },
    {
        "label": "LEFT HIP",
        "x": 69.19999999999999,
        "y": 81.5
    },
    {
        "label": "LEFT SHOULDER",
        "x": 70.5,
        "y": 70.2
    },
    {
        "label": "LEFT ELBOW",
        "x": 73.19999999999999,
        "y": 75.1
    },
    {
        "label": "LEFT ARM",
        "x": 73.6,
        "y": 79.3
    },
    {
        "label": "LEFT EYE",
        "x": 68.19999999999999,
        "y": 65.6
    },
    {
        "label": "LEFT EAR",
        "x": 72.1,
        "y": 62.2
    },
    {
        "label": "NOSE",
        "x": 64.1,
        "y": 67.2
    },
    {
        "label": "NECK",
        "x": 64.1,
        "y": 69.5
    }
]